cgi_utils.py
cgi_utils-0.1.0.dist-info/LICENSE
cgi_utils-0.1.0.dist-info/METADATA
cgi_utils-0.1.0.dist-info/WHEEL
cgi_utils-0.1.0.dist-info/top_level.txt
cgi_utils-0.1.0.dist-info/zip-safe
cgi_utils-0.1.0.dist-info/RECORD
