Metadata-Version: 2.1
Name: cgi-utils
Version: 0.1.0
Summary: A minimal CGI library
Home-page: https://github.com/zeevro/cgi_utils
Author: Zeev Rotshtein
Author-email: zeevro@gmail.com
Maintainer: Zeev Rotshtein
Maintainer-email: zeevro@gmail.com
License: UNKNOWN
Download-URL: https://github.com/zeevro/cgi_utils/archive/master.zip
Keywords: Web,CGI
Platform: UNKNOWN
Classifier: Development Status :: 4 - Beta
Classifier: License :: Public Domain
Classifier: Natural Language :: English
Classifier: Programming Language :: Python
Classifier: Programming Language :: Python :: 3
Classifier: Programming Language :: Python :: 3 :: Only
Classifier: Topic :: Internet :: WWW/HTTP :: Dynamic Content :: CGI Tools/Libraries
